h11/__init__.py
h11/_abnf.py
h11/_connection.py
h11/_events.py
h11/_headers.py
h11/_readers.py
h11/_receivebuffer.py
h11/_state.py
h11/_util.py
h11/_version.py
h11/_writers.py
h11/tests/__init__.py
h11/tests/helpers.py
h11/tests/test_against_stdlib_http.py
h11/tests/test_connection.py
h11/tests/test_events.py
h11/tests/test_headers.py
h11/tests/test_helpers.py
h11/tests/test_io.py
h11/tests/test_receivebuffer.py
h11/tests/test_state.py
h11/tests/test_util.py
h11/tests/data/test-file
h11-0.10.0.dist-info/LICENSE.txt
h11-0.10.0.dist-info/METADATA
h11-0.10.0.dist-info/WHEEL
h11-0.10.0.dist-info/top_level.txt
h11-0.10.0.dist-info/RECORD
